
                {"ruleset":[
                
                            
                                {"rule": ["","Ⅎ","Ⅎ"], "type": "level"},
                            
                                {"rule": ["","ⅎ","ⅎ"], "type": "level"},
                            
                                {"rule": ["","℞","℞"], "type": "level"},
                            
                                {"rule": ["","℟","℟"], "type": "level"},
                            
                                {"rule": ["","℣","℣"], "type": "level"},
                            
                                {"rule": ["","℔","℔"], "type": "level"},
                            
                                {"rule": ["","℈","℈"], "type": "level"},
                            
                                {"rule": ["","℥","℥"], "type": "level"}
                ]}
            