
                    P1:&lt;ruleset&gt;"ᴀ",ᴀleve</ruleset>&lt;ruleset&gt;"ᴁ",ᴁleve</ruleset>&lt;ruleset&gt;"ᴄ",ᴄleve</ruleset>&lt;ruleset&gt;"ᴅ",ᴅleve</ruleset>&lt;ruleset&gt;"ᴆ",ᴆleve</ruleset>&lt;ruleset&gt;"ᴇ",ᴇleve</ruleset>&lt;ruleset&gt;"ᵹ",ᵹleve</ruleset>&lt;ruleset&gt;"ᴊ",ᴊleve</ruleset>&lt;ruleset&gt;"ᴋ",ᴋleve</ruleset>&lt;ruleset&gt;"ᴍ",ᴍleve</ruleset>&lt;ruleset&gt;"ᴏ",ᴏleve</ruleset>&lt;ruleset&gt;"ᴘ",ᴘleve</ruleset>&lt;ruleset&gt;"ᴛ",ᴛleve</ruleset>&lt;ruleset&gt;"ᴜ",ᴜleve</ruleset>&lt;ruleset&gt;ᵫ"ᵫ",ᵫleve</ruleset>&lt;ruleset&gt;"ᴠ",ᴠleve</ruleset>&lt;ruleset&gt;"ᴡ",ᴡleve</ruleset>&lt;ruleset&gt;"ᴢ",ᴢleve</ruleset>&lt;ruleset&gt;"ᴵ",ᴵleve</ruleset>
                    P2:<line>&lt;ruleset&gt;<rule/><rule>"ᴀ",</rule><rule>ᴀ</rule><type>leve</type><xkomma/>&lt;ruleset&gt;<rule/><rule>"ᴁ",</rule><rule>ᴁ</rule><type>leve</type><xkomma/>&lt;ruleset&gt;<rule/><rule>"ᴄ",</rule><rule>ᴄ</rule><type>leve</type><xkomma/>&lt;ruleset&gt;<rule/><rule>"ᴅ",</rule><rule>ᴅ</rule><type>leve</type><xkomma/>&lt;ruleset&gt;<rule/><rule>"ᴆ",</rule><rule>ᴆ</rule><type>leve</type><xkomma/>&lt;ruleset&gt;<rule/><rule>"ᴇ",</rule><rule>ᴇ</rule><type>leve</type><xkomma/>&lt;ruleset&gt;<rule/><rule>"ᵹ",</rule><rule>ᵹ</rule><type>leve</type><xkomma/>&lt;ruleset&gt;<rule/><rule>"ᴊ",</rule><rule>ᴊ</rule><type>leve</type><xkomma/>&lt;ruleset&gt;<rule/><rule>"ᴋ",</rule><rule>ᴋ</rule><type>leve</type><xkomma/>&lt;ruleset&gt;<rule/><rule>"ᴍ",</rule><rule>ᴍ</rule><type>leve</type><xkomma/>&lt;ruleset&gt;<rule/><rule>"ᴏ",</rule><rule>ᴏ</rule><type>leve</type><xkomma/>&lt;ruleset&gt;<rule/><rule>"ᴘ",</rule><rule>ᴘ</rule><type>leve</type><xkomma/>&lt;ruleset&gt;<rule/><rule>"ᴛ",</rule><rule>ᴛ</rule><type>leve</type><xkomma/>&lt;ruleset&gt;<rule/><rule>"ᴜ",</rule><rule>ᴜ</rule><type>leve</type><xkomma/>&lt;ruleset&gt;<rule>ᵫ</rule><rule>"ᵫ",</rule><rule>ᵫ</rule><type>leve</type><xkomma/>&lt;ruleset&gt;<rule/><rule>"ᴠ",</rule><rule>ᴠ</rule><type>leve</type><xkomma/>&lt;ruleset&gt;<rule/><rule>"ᴡ",</rule><rule>ᴡ</rule><type>leve</type><xkomma/>&lt;ruleset&gt;<rule/><rule>"ᴢ",</rule><rule>ᴢ</rule><type>leve</type><xkomma/>&lt;ruleset&gt;<rule/><rule>"ᴵ",</rule><rule>ᴵ</rule><type>leve</type><xkomma/></line>