aaalevel<ruleset>level</ruleset><ruleset>level</ruleset><ruleset>level</ruleset><ruleset>level</ruleset><ruleset>level</ruleset><ruleset>level</ruleset><ruleset>level</ruleset><ruleset>level</ruleset><ruleset>level</ruleset><ruleset>level</ruleset><ruleset>level</ruleset><ruleset>level</ruleset><ruleset>level</ruleset><ruleset>level</ruleset><ruleset>level</ruleset><ruleset>level</ruleset><ruleset>level</ruleset><ruleset>level</ruleset><ruleset>level</ruleset><ruleset>level</ruleset><ruleset>ck"ck",level</ruleset><ruleset>ct"ct",level</ruleset><ruleset>ch"ch",level</ruleset><ruleset>level</ruleset><ruleset>level</ruleset><ruleset>fj"fj",level</ruleset><ruleset>level</ruleset><ruleset>ft"ft",level</ruleset><ruleset>level</ruleset><ruleset>level</ruleset><ruleset>level</ruleset><ruleset>level</ruleset><ruleset>level</ruleset><ruleset>level</ruleset><ruleset>level</ruleset><ruleset>level</ruleset><ruleset>level</ruleset><ruleset>level</ruleset><ruleset>level</ruleset><ruleset>level</ruleset><ruleset>level</ruleset><ruleset>level</ruleset><ruleset>level</ruleset><ruleset>level</ruleset><ruleset>ll"ll",level</ruleset><ruleset>level</ruleset><ruleset>level</ruleset><ruleset>level</ruleset><ruleset>level</ruleset><ruleset>level</ruleset><ruleset>level</ruleset><ruleset>level</ruleset><ruleset>level</ruleset><ruleset>level</ruleset><ruleset>level</ruleset><ruleset>level</ruleset><ruleset>level</ruleset><ruleset>level</ruleset><ruleset>level</ruleset><ruleset>ſi"ſi",level</ruleset><ruleset>level</ruleset><ruleset>level</ruleset><ruleset>level</ruleset><ruleset>ſſ"ſſ",level</ruleset><ruleset>level</ruleset><ruleset>level</ruleset><ruleset>level</ruleset><ruleset>level</ruleset><ruleset>level</ruleset><ruleset>level</ruleset><ruleset>level</ruleset><ruleset>level</ruleset><ruleset>ſch"ſch",level</ruleset><ruleset>level</ruleset><ruleset>level</ruleset><ruleset>level</ruleset><ruleset>level</ruleset><ruleset>level</ruleset><ruleset>level</ruleset><ruleset>tt"tt",level</ruleset><ruleset>level</ruleset><ruleset>level</ruleset><ruleset>level</ruleset><ruleset>level</ruleset><ruleset>level</ruleset><ruleset>level</ruleset><ruleset>level</ruleset><ruleset>level</ruleset><ruleset>level</ruleset>