<?xml version="1.0" encoding="UTF-8"?><range>PUA-20</range><rule></rule><rule>Æ̈</rule><rule></rule><type>level</type></ruleset><range>PUA-20</range><rule></rule><rule>æ̈</rule><rule></rule><type>level</type></ruleset><range>PUA-20</range><rule></rule><rule></rule><rule></rule><type>level</type></ruleset><range>PUA-20</range><rule></rule><rule>̈</rule><rule></rule><type>level</type></ruleset><range>PUA-20</range><rule></rule><rule>̈</rule><rule></rule><type>level</type></ruleset><range>PUA-20</range><rule></rule><rule>J̈</rule><rule></rule><type>level</type></ruleset><range>PUA-20</range><rule></rule><rule>j̈</rule><rule></rule><type>level</type></ruleset><range>PUA-20</range><rule></rule><rule></rule><rule></rule><type>level</type></ruleset><range>PUA-20</range><rule></rule><rule>̈</rule><rule></rule><type>level</type></ruleset><range>PUA-20</range><rule></rule><rule>̈</rule><rule></rule><type>level</type></ruleset><range>PUA-20</range><rule></rule><rule>̈</rule><rule></rule><type>level</type></ruleset><range>PUA-20</range><rule></rule><rule>̈</rule><rule></rule><type>level</type></ruleset><range>PUA-20</range><rule></rule><rule>V̈</rule><rule></rule><type>level</type></ruleset><range>PUA-20</range><rule></rule><rule>v̈</rule><rule></rule><type>level</type></ruleset><range>PUA-20</range><rule></rule><rule>̈</rule><rule></rule><type>level</type></ruleset><range>PUA-20</range><rule></rule><rule>̈</rule><rule></rule><type>level</type></ruleset>