
                    P1:<ruleset>"Ȧ́",level</ruleset><ruleset>"ȧ́",level</ruleset><ruleset>"Æ̇́",level</ruleset><ruleset>"æ̇́",level</ruleset><ruleset>"Ė́",level</ruleset><ruleset>"ė́",level</ruleset><ruleset>"İ́",level</ruleset><ruleset>"i̇́",level</ruleset><ruleset>"Ȯ́",level</ruleset><ruleset>"ȯ́",level</ruleset><ruleset>"Ø̇́",level</ruleset><ruleset>"ø̇́",level</ruleset><ruleset>"U̇́",level</ruleset><ruleset>"u̇́",level</ruleset><ruleset>"Ẏ́",level</ruleset><ruleset>"ẏ́",level</ruleset>
                    P2:<line><olevel/><rule/><rule>"Ȧ́",</rule><rule></rule><type>level</type><clevel/><olevel/><rule/><rule>"ȧ́",</rule><rule></rule><type>level</type><clevel/><olevel/><rule/><rule>"Æ̇́",</rule><rule></rule><type>level</type><clevel/><olevel/><rule/><rule>"æ̇́",</rule><rule></rule><type>level</type><clevel/><olevel/><rule/><rule>"Ė́",</rule><rule></rule><type>level</type><clevel/><olevel/><rule/><rule>"ė́",</rule><rule></rule><type>level</type><clevel/><olevel/><rule/><rule>"İ́",</rule><rule></rule><type>level</type><clevel/><olevel/><rule/><rule>"i̇́",</rule><rule></rule><type>level</type><clevel/><olevel/><rule/><rule>"Ȯ́",</rule><rule></rule><type>level</type><clevel/><olevel/><rule/><rule>"ȯ́",</rule><rule></rule><type>level</type><clevel/><olevel/><rule/><rule>"Ø̇́",</rule><rule></rule><type>level</type><clevel/><olevel/><rule/><rule>"ø̇́",</rule><rule></rule><type>level</type><clevel/><olevel/><rule/><rule>"U̇́",</rule><rule></rule><type>level</type><clevel/><olevel/><rule/><rule>"u̇́",</rule><rule></rule><type>level</type><clevel/><olevel/><rule/><rule>"Ẏ́",</rule><rule></rule><type>level</type><clevel/><olevel/><rule/><rule>"ẏ́",</rule><rule></rule><type>level</type><clevel/></line>