
                    P1:&lt;ruleset&gt;"ᚨ",ᚨleve</ruleset>&lt;ruleset&gt;"ᚧ",ᚧleve</ruleset>&lt;ruleset&gt;"ᚠ",ᚠleve</ruleset>&lt;ruleset&gt;"ᚢ",ᚢleve</ruleset>&lt;ruleset&gt;"ᚡ",ᚡleve</ruleset>&lt;ruleset&gt;"ᚥ",ᚥleve</ruleset>&lt;ruleset&gt;"ᚣ",ᚣleve</ruleset>&lt;ruleset&gt;"ᚤ",ᚤleve</ruleset>&lt;ruleset&gt;"ᛘ",ᛘleve</ruleset>&lt;ruleset&gt;"ᚦ",ᚦleve</ruleset>
                    P2:<line>&lt;ruleset&gt;<rule/><rule>"ᚨ",</rule><rule>ᚨ</rule><type>leve</type><xkomma/>&lt;ruleset&gt;<rule/><rule>"ᚧ",</rule><rule>ᚧ</rule><type>leve</type><xkomma/>&lt;ruleset&gt;<rule/><rule>"ᚠ",</rule><rule>ᚠ</rule><type>leve</type><xkomma/>&lt;ruleset&gt;<rule/><rule>"ᚢ",</rule><rule>ᚢ</rule><type>leve</type><xkomma/>&lt;ruleset&gt;<rule/><rule>"ᚡ",</rule><rule>ᚡ</rule><type>leve</type><xkomma/>&lt;ruleset&gt;<rule/><rule>"ᚥ",</rule><rule>ᚥ</rule><type>leve</type><xkomma/>&lt;ruleset&gt;<rule/><rule>"ᚣ",</rule><rule>ᚣ</rule><type>leve</type><xkomma/>&lt;ruleset&gt;<rule/><rule>"ᚤ",</rule><rule>ᚤ</rule><type>leve</type><xkomma/>&lt;ruleset&gt;<rule/><rule>"ᛘ",</rule><rule>ᛘ</rule><type>leve</type><xkomma/>&lt;ruleset&gt;<rule/><rule>"ᚦ",</rule><rule>ᚦ</rule><type>leve</type><xkomma/></line>