
                    P1:&lt;ruleset&gt;"⁰",⁰leve</ruleset>&lt;ruleset&gt;"⁴",⁴leve</ruleset>&lt;ruleset&gt;"⁵",⁵leve</ruleset>&lt;ruleset&gt;"⁶",⁶leve</ruleset>&lt;ruleset&gt;"⁷",⁷leve</ruleset>&lt;ruleset&gt;"⁸",⁸leve</ruleset>&lt;ruleset&gt;"⁹",⁹leve</ruleset>&lt;ruleset&gt;"₀",₀leve</ruleset>&lt;ruleset&gt;"₁",₁leve</ruleset>&lt;ruleset&gt;"₂",₂leve</ruleset>&lt;ruleset&gt;"₃",₃leve</ruleset>&lt;ruleset&gt;"₄",₄leve</ruleset>&lt;ruleset&gt;"₅",₅leve</ruleset>&lt;ruleset&gt;"₆",₆leve</ruleset>&lt;ruleset&gt;"₇",₇leve</ruleset>&lt;ruleset&gt;"₈",₈leve</ruleset>&lt;ruleset&gt;"₉",₉leve</ruleset>&lt;ruleset&gt;"⁻",⁻leve</ruleset>
                    P2:<line>&lt;ruleset&gt;<rule/><rule>"⁰",</rule><rule>⁰</rule><type>leve</type><xkomma/>&lt;ruleset&gt;<rule/><rule>"⁴",</rule><rule>⁴</rule><type>leve</type><xkomma/>&lt;ruleset&gt;<rule/><rule>"⁵",</rule><rule>⁵</rule><type>leve</type><xkomma/>&lt;ruleset&gt;<rule/><rule>"⁶",</rule><rule>⁶</rule><type>leve</type><xkomma/>&lt;ruleset&gt;<rule/><rule>"⁷",</rule><rule>⁷</rule><type>leve</type><xkomma/>&lt;ruleset&gt;<rule/><rule>"⁸",</rule><rule>⁸</rule><type>leve</type><xkomma/>&lt;ruleset&gt;<rule/><rule>"⁹",</rule><rule>⁹</rule><type>leve</type><xkomma/>&lt;ruleset&gt;<rule/><rule>"₀",</rule><rule>₀</rule><type>leve</type><xkomma/>&lt;ruleset&gt;<rule/><rule>"₁",</rule><rule>₁</rule><type>leve</type><xkomma/>&lt;ruleset&gt;<rule/><rule>"₂",</rule><rule>₂</rule><type>leve</type><xkomma/>&lt;ruleset&gt;<rule/><rule>"₃",</rule><rule>₃</rule><type>leve</type><xkomma/>&lt;ruleset&gt;<rule/><rule>"₄",</rule><rule>₄</rule><type>leve</type><xkomma/>&lt;ruleset&gt;<rule/><rule>"₅",</rule><rule>₅</rule><type>leve</type><xkomma/>&lt;ruleset&gt;<rule/><rule>"₆",</rule><rule>₆</rule><type>leve</type><xkomma/>&lt;ruleset&gt;<rule/><rule>"₇",</rule><rule>₇</rule><type>leve</type><xkomma/>&lt;ruleset&gt;<rule/><rule>"₈",</rule><rule>₈</rule><type>leve</type><xkomma/>&lt;ruleset&gt;<rule/><rule>"₉",</rule><rule>₉</rule><type>leve</type><xkomma/>&lt;ruleset&gt;<rule/><rule>"⁻",</rule><rule>⁻</rule><type>leve</type><xkomma/></line>